aicard_eval/__init__.py
aicard_eval/emissions.py
aicard_eval/experiments.py
aicard_eval/metrics.py
aicard_eval/utils.py
aicard_eval/card/__init__.py
aicard_eval/card/dot_dict.py
aicard_eval/card/fields.py
aicard_eval/card/model_card.py
aicard_eval/tasks/__init__.py
aicard_eval/tasks/base.py
aicard_eval/tasks/multimodal.py
aicard_eval/tasks/nlp.py
aicard_eval/tasks/vision.py
aicard_eval/tasks/params/__init__.py
aicard_eval/tasks/params/classification.py
aicard_eval/tasks/params/object_detection.py
aicard_eval/tasks/params/unknown.py
aicard_eval-0.1.2.dist-info/licenses/LICENSE
aicard_eval-0.1.2.dist-info/METADATA
aicard_eval-0.1.2.dist-info/WHEEL
aicard_eval-0.1.2.dist-info/top_level.txt
aicard_eval-0.1.2.dist-info/RECORD
