Metadata-Version: 2.4
Name: aicard-eval
Version: 0.1.2
Summary: Evaluation module for aicard.
Home-page: https://github.com/mever-team/aicard-eval
Author: CERTH
Author-email: gnikoul@gmail.com
Classifier: Programming Language :: Python :: 3
Classifier: License :: OSI Approved :: MIT License
Classifier: Operating System :: OS Independent
Classifier: Intended Audience :: Developers
Classifier: Development Status :: 2 - Pre-Alpha
Requires-Python: >=3.11
License-File: LICENSE
Requires-Dist: datasets
Requires-Dist: numpy
Requires-Dist: validators
Requires-Dist: scikit-learn
Requires-Dist: scikit-image
Requires-Dist: jiwer
Requires-Dist: psutil
Requires-Dist: od-metrics
Requires-Dist: eco2ai
Requires-Dist: html2text
Requires-Dist: markdown2
Dynamic: author
Dynamic: author-email
Dynamic: classifier
Dynamic: description
Dynamic: description-content-type
Dynamic: home-page
Dynamic: license-file
Dynamic: requires-dist
Dynamic: requires-python
Dynamic: summary
